ordercost/__init__.py
ordercost/ordercost.py
ordercost-0.0.1.dist-info/METADATA
ordercost-0.0.1.dist-info/WHEEL
ordercost-0.0.1.dist-info/top_level.txt
ordercost-0.0.1.dist-info/RECORD
