Metadata-Version: 2.4
Name: ordercost
Version: 0.0.1
Summary: This package helps to Calculate total cost of an order based on selected product and quantity
Author-email: Riteshclinton <Ritclin12@gmail.com>
Requires-Python: >=3.7
Requires-Dist: boto3
